{
"Family":"Caprifoliaceae",
"ScientificName":"Lonicera japonica",
"CommonNames":"",
"Synonyms":"",
"PlantForm":"Woody climber or scrambler.",
"Size":"Up to 10m high when climbing.",
"Stem":"Young stems purplish and densely hairy, older stems brown and hairless.",
"Leaves":"Dark green upper and paler below, 3-8 cm long, oval shaped, in opposite pairs on stems, with smooth edges and sometimes deeply lobed when young.",
"Flowers":"Tubular, white to pink, turing yellow or orange with age, in pairs at leaf bases, very fragrant.",
"FruitSeeds":"Oval shaped, shiny black berries.",
"Habitat":"Forests, woodlands, along streams, heathlands, disturbed areas.",
"DistinguishingFeatures":"Unlikely to be confused when in flower.",
"Photos":[
{"FileName":"8696_P6880843.jpg","Caption":"Flowers are white, then yellow"},
{"FileName":"74945_P1086701.jpg","Caption":"Leaves"},
{"FileName":"13224_ACTFC.jpg","Caption":"Infestation"},
{"FileName":"8707_P6880857.jpg","Caption":"Rambles over other plants"}
]
}
