{
"Family":"Araceae",
"ScientificName":"Pistia stratiotes",
"CommonNames":"water lettuce",
"Synonyms":"",
"PlantForm":"Aquatic mat-forming, floating herb.",
"Size":"Up to 30 cm across.",
"Stem":"Horizontal runners producing new plants.",
"Leaves":"Undivided, widest near end, partly overlapping each other, up to 17 cm long, longitudinally ribbed, softly hairy, with short, inflated stalk. Has an overall lettuce-like appearance.",
"Flowers":"Inconspicuous, between leaf bases, whitish-greenish, up to 2 cm wide.",
"FruitSeeds":"Greenish berry 5-10 mm across.",
"Habitat":"Ponds, lagoons, wetlands.",
"DistinguishingFeatures":"",
"Impacts":"",
"Photos":[
{"FileName":"103991_IMG_8099.jpg","Caption":"Plants are large when not chewed by insects"},
{"FileName":"106804_P1278119.jpg","Caption":"Damaged plants are smaller"},
{"FileName":"122088_P1285771.jpg","Caption":"Forms dense floating mats"},
{"FileName":"158205_Pistia_stratiotes_changkt_CC_127654828.jpeg","Caption":"Flowers are inconspicuous"}
]
}
