{
"Family":"Rubiaceae",
"ScientificName":"Galium aparine",
"CommonNames":"Cleavers",
"Synonyms":"",
"PlantForm":"Scrambling to climbing annual herb.",
"Size":"Up to 1.5 m long.",
"Stem":"With backwards-pointing prickles along the edges.",
"Leaves":"In whorls of 6-9, undivided, up to 6 cm, with backwards curving hairs on margins and hooked hairs on surfaces.",
"Flowers":"In small branched groupings of 2-7, tiny, white, with four petals.",
"FruitSeeds":"Dry, 3-5 mm across, with many hooked hairs that attach to clothes and fur.",
"Habitat":"Parks, bushland, forests, disturbed areas, riparian areas.",
"DistinguishingFeatures":"Combination of leaves in whorls and the hooked, burr-like hairs on leaves and fruits distinguish from other Bedstraws (*Galium* species).",
"Impacts":"",
"Photos":[
{"FileName":"8710_P6880860.jpg","Caption":"Leaves are in whorls"},
{"FileName":"8396_P6880642.jpg","Caption":"Rambles over ground and low objects"},
{"FileName":"65206_P1042855.jpg","Caption":"Round burr-like fruit"},
{"FileName":"176289_P1463166.jpg","Caption":"Dies back in winter"}
]
}
